{
  "lastUpdated": "2025-09-10T00:00:32.631Z",
  "stats": {
    "users": {
      "count": 133917,
      "change": 6.5
    },
    "revenue": {
      "amount": 469069,
      "change": -0.3
    },
    "projects": {
      "count": 372,
      "change": -1.2
    },
    "tasks": {
      "count": 2862,
      "change": 12.7
    }
  },
  "activities": [
    {
      "type": "user",
      "title": "Project created",
      "timestamp": "2025-09-10T00:00:32.631Z"
    },
    {
      "type": "user",
      "title": "Task completed",
      "timestamp": "2025-09-09T00:00:05.439Z"
    },
    {
      "type": "alert",
      "title": "System alert",
      "timestamp": "2025-09-08T00:00:35.594Z"
    },
    {
      "type": "payment",
      "title": "Project milestone reached",
      "timestamp": "2025-09-07T00:00:34.976Z"
    },
    {
      "type": "user",
      "title": "Payment received",
      "timestamp": "2025-09-06T00:00:12.335Z"
    }
  ],
  "weeklyActivity": [
    {
      "day": "Mon",
      "value": 84
    },
    {
      "day": "Tue",
      "value": 38
    },
    {
      "day": "Wed",
      "value": 10
    },
    {
      "day": "Thu",
      "value": 100
    },
    {
      "day": "Fri",
      "value": 10
    },
    {
      "day": "Sat",
      "value": 59
    },
    {
      "day": "Sun",
      "value": 57
    }
  ],
  "performanceMetrics": [
    {
      "date": "2023-11-30",
      "value": 37
    },
    {
      "date": "2023-12-01",
      "value": 39
    },
    {
      "date": "2023-12-02",
      "value": 32
    },
    {
      "date": "2023-12-03",
      "value": 24
    },
    {
      "date": "2023-12-04",
      "value": 45
    },
    {
      "date": "2023-12-05",
      "value": 14
    },
    {
      "date": "2023-12-06",
      "value": 17
    }
  ]
}