{
  "lastUpdated": "2026-01-28T00:00:15.216Z",
  "stats": {
    "users": {
      "count": 927645,
      "change": 14.7
    },
    "revenue": {
      "amount": 1460393,
      "change": 5
    },
    "projects": {
      "count": 397,
      "change": -3.3
    },
    "tasks": {
      "count": 3842,
      "change": 2
    }
  },
  "activities": [
    {
      "type": "user",
      "title": "Project milestone reached",
      "timestamp": "2026-01-28T00:00:15.216Z"
    },
    {
      "type": "project",
      "title": "User updated profile",
      "timestamp": "2026-01-27T00:00:42.539Z"
    },
    {
      "type": "user",
      "title": "Project milestone reached",
      "timestamp": "2026-01-26T00:00:51.238Z"
    },
    {
      "type": "message",
      "title": "New user registered",
      "timestamp": "2026-01-25T00:00:52.328Z"
    },
    {
      "type": "payment",
      "title": "New message",
      "timestamp": "2026-01-24T00:00:58.623Z"
    }
  ],
  "weeklyActivity": [
    {
      "day": "Mon",
      "value": 41
    },
    {
      "day": "Tue",
      "value": 58
    },
    {
      "day": "Wed",
      "value": 51
    },
    {
      "day": "Thu",
      "value": 57
    },
    {
      "day": "Fri",
      "value": 14
    },
    {
      "day": "Sat",
      "value": 45
    },
    {
      "day": "Sun",
      "value": 10
    }
  ],
  "performanceMetrics": [
    {
      "date": "2024-02-17",
      "value": 26
    },
    {
      "date": "2024-02-18",
      "value": 27
    },
    {
      "date": "2024-02-19",
      "value": 46
    },
    {
      "date": "2024-02-20",
      "value": 33
    },
    {
      "date": "2024-02-21",
      "value": 40
    },
    {
      "date": "2024-02-22",
      "value": 46
    },
    {
      "date": "2024-02-23",
      "value": 29
    }
  ]
}