{
  "lastUpdated": "2025-09-15T00:00:24.416Z",
  "stats": {
    "users": {
      "count": 146930,
      "change": 14.5
    },
    "revenue": {
      "amount": 502981,
      "change": 0.2
    },
    "projects": {
      "count": 374,
      "change": -2
    },
    "tasks": {
      "count": 2965,
      "change": 5
    }
  },
  "activities": [
    {
      "type": "project",
      "title": "User updated profile",
      "timestamp": "2025-09-15T00:00:24.416Z"
    },
    {
      "type": "message",
      "title": "System alert",
      "timestamp": "2025-09-14T00:00:55.953Z"
    },
    {
      "type": "payment",
      "title": "Invoice generated",
      "timestamp": "2025-09-13T00:00:35.169Z"
    },
    {
      "type": "project",
      "title": "Task assigned",
      "timestamp": "2025-09-12T00:00:54.112Z"
    },
    {
      "type": "task",
      "title": "Payment received",
      "timestamp": "2025-09-11T00:00:13.712Z"
    }
  ],
  "weeklyActivity": [
    {
      "day": "Mon",
      "value": 71
    },
    {
      "day": "Tue",
      "value": 40
    },
    {
      "day": "Wed",
      "value": 12
    },
    {
      "day": "Thu",
      "value": 95
    },
    {
      "day": "Fri",
      "value": 23
    },
    {
      "day": "Sat",
      "value": 37
    },
    {
      "day": "Sun",
      "value": 22
    }
  ],
  "performanceMetrics": [
    {
      "date": "2023-12-05",
      "value": 14
    },
    {
      "date": "2023-12-06",
      "value": 17
    },
    {
      "date": "2023-12-07",
      "value": 36
    },
    {
      "date": "2023-12-08",
      "value": 46
    },
    {
      "date": "2023-12-09",
      "value": 44
    },
    {
      "date": "2023-12-10",
      "value": 24
    },
    {
      "date": "2023-12-11",
      "value": 28
    }
  ]
}