{
  "lastUpdated": "2025-08-24T00:00:54.305Z",
  "stats": {
    "users": {
      "count": 86346,
      "change": -3.3
    },
    "revenue": {
      "amount": 365610,
      "change": 9.2
    },
    "projects": {
      "count": 368,
      "change": 4.2
    },
    "tasks": {
      "count": 2727,
      "change": 17.1
    }
  },
  "activities": [
    {
      "type": "project",
      "title": "System alert",
      "timestamp": "2025-08-24T00:00:54.305Z"
    },
    {
      "type": "user",
      "title": "User updated profile",
      "timestamp": "2025-08-23T00:01:30.870Z"
    },
    {
      "type": "task",
      "title": "Invoice generated",
      "timestamp": "2025-08-22T00:00:20.460Z"
    },
    {
      "type": "message",
      "title": "New message",
      "timestamp": "2025-08-21T00:00:29.747Z"
    },
    {
      "type": "user",
      "title": "Invoice generated",
      "timestamp": "2025-08-20T00:00:13.143Z"
    }
  ],
  "weeklyActivity": [
    {
      "day": "Mon",
      "value": 56
    },
    {
      "day": "Tue",
      "value": 14
    },
    {
      "day": "Wed",
      "value": 14
    },
    {
      "day": "Thu",
      "value": 93
    },
    {
      "day": "Fri",
      "value": 33
    },
    {
      "day": "Sat",
      "value": 19
    },
    {
      "day": "Sun",
      "value": 94
    }
  ],
  "performanceMetrics": [
    {
      "date": "2023-11-13",
      "value": 24
    },
    {
      "date": "2023-11-14",
      "value": 36
    },
    {
      "date": "2023-11-15",
      "value": 20
    },
    {
      "date": "2023-11-16",
      "value": 18
    },
    {
      "date": "2023-11-17",
      "value": 17
    },
    {
      "date": "2023-11-18",
      "value": 24
    },
    {
      "date": "2023-11-19",
      "value": 29
    }
  ]
}